{"id":"600015611_26-41-L/01","as_p1":{"total":14,"backup_p2":[{"id":"600015611_23-44-L/01","count":4,"pct":28.6,"nazev":"MESIT střední škola, Družstevní","obor":"Mechanik strojů a zařízení","obec":"Uherské Hradiště","min_body":40},{"id":"600015611_26-52-H/01","count":3,"pct":21.4,"nazev":"600015611","obor":"","obec":"","min_body":0}],"backup_p3":[{"id":"600015611_26-51-H/02","count":6,"pct":42.9,"nazev":"600015611","obor":"","obec":"","min_body":0}]},"as_p2":{"total":21,"preferred_p1":[{"id":"600015459_26-41-M/01","count":4,"pct":19.0,"nazev":"SŠ prům., Jiřího z Poděbrad","obor":"Elektrotechnika","obec":"Uherské Hradiště","min_body":78},{"id":"600015459_23-41-M/01","count":3,"pct":14.3,"nazev":"SŠ prům., Jiřího z Poděbrad","obor":"Strojírenství","obec":"Uherské Hradiště","min_body":36},{"id":"650008006_23-45-L/02","count":3,"pct":14.3,"nazev":"Střední škola letecká s.r.o., Na Záhonech","obor":"Letecký mechanik","obec":"Kunovice","min_body":80}],"backup_p3":[{"id":"600015611_26-51-H/02","count":7,"pct":33.3,"nazev":"600015611","obor":"","obec":"","min_body":0}]},"as_p3":{"total":14,"preferred_p1":[{"id":"600015459_26-41-M/01","count":5,"pct":35.7,"nazev":"SŠ prům., Jiřího z Poděbrad","obor":"Elektrotechnika","obec":"Uherské Hradiště","min_body":78}],"preferred_p2":[{"id":"600015459_26-41-M/01","count":3,"pct":21.4,"nazev":"SŠ prům., Jiřího z Poděbrad","obor":"Elektrotechnika","obec":"Uherské Hradiště","min_body":78}]}}