{"id":"600016579_18-20-M/01","as_p1":{"total":63,"backup_p2":[{"id":"600016579_26-41-M/01","count":12,"pct":19.0,"nazev":"SPŠ elektrotechnická, Makarenkova","obor":"Elektrotechnika","obec":"Havířov","min_body":72},{"id":"600016536_18-20-M/01","count":6,"pct":9.5,"nazev":"Gymnázium a Obchodní akademie, Masarykova třída","obor":"Informační technologie","obec":"Orlová","min_body":40},{"id":"600017583_18-20-M/01","count":6,"pct":9.5,"nazev":"SPŠ elektrotechniky a informatiky, Kratochvílova","obor":"Informační technologie","obec":"Ostrava","min_body":56},{"id":"600016552_36-47-M/01","count":5,"pct":7.9,"nazev":"SPŠ stavební, Kollárova","obor":"Stavebnictví","obec":"Havířov","min_body":60},{"id":"600016676_18-20-M/01","count":5,"pct":7.9,"nazev":"Střední průmyslová škola, Žižkova","obor":"Informační technologie","obec":"Karviná","min_body":68},{"id":"600016374_18-20-M/01","count":4,"pct":6.3,"nazev":"Střední škola inform.technologií, Pionýrů","obor":"Informační technologie","obec":"Frýdek-Místek","min_body":46},{"id":"600016340_18-20-M/01","count":3,"pct":4.8,"nazev":"TŘINECKÁ OBCHODNÍ AKADEMIE IT a VS, Beskydská","obor":"Informační technologie","obec":"Třinec","min_body":22},{"id":"600016587_18-20-M/01","count":3,"pct":4.8,"nazev":"SOŠ NET OFFICE Orlová, Energetiků","obor":"Informační technologie","obec":"Orlová","min_body":54},{"id":"600016510_26-41-M/01","count":3,"pct":4.8,"nazev":"Střední škola polytechnická, Sýkorova","obor":"Elektrotechnika","obec":"Havířov","min_body":36}],"backup_p3":[{"id":"600016510_26-41-M/01","count":6,"pct":9.5,"nazev":"Střední škola polytechnická, Sýkorova","obor":"Elektrotechnika","obec":"Havířov","min_body":36},{"id":"600016552_36-47-M/01","count":6,"pct":9.5,"nazev":"SPŠ stavební, Kollárova","obor":"Stavebnictví","obec":"Havířov","min_body":60},{"id":"600016536_18-20-M/01","count":4,"pct":6.3,"nazev":"Gymnázium a Obchodní akademie, Masarykova třída","obor":"Informační technologie","obec":"Orlová","min_body":40},{"id":"600016510_26-41-L/01","count":4,"pct":6.3,"nazev":"Střední škola polytechnická, Sýkorova","obor":"Mechanik elektrotechnik","obec":"Havířov","min_body":24},{"id":"600016579_26-41-M/01","count":4,"pct":6.3,"nazev":"SPŠ elektrotechnická, Makarenkova","obor":"Elektrotechnika","obec":"Havířov","min_body":72},{"id":"600016676_18-20-M/01","count":4,"pct":6.3,"nazev":"Střední průmyslová škola, Žižkova","obor":"Informační technologie","obec":"Karviná","min_body":68},{"id":"600016340_18-20-M/01","count":3,"pct":4.8,"nazev":"TŘINECKÁ OBCHODNÍ AKADEMIE IT a VS, Beskydská","obor":"Informační technologie","obec":"Třinec","min_body":22},{"id":"600016323_23-41-M/01","count":3,"pct":4.8,"nazev":"SPŠ, 28. října","obor":"Strojírenství","obec":"Frýdek-Místek","min_body":48},{"id":"600016641_63-41-M/02","count":3,"pct":4.8,"nazev":"Hotelová škola a Obchodní akademie s.r.o, Tajovského","obor":"Obchodní akademie","obec":"Havířov","min_body":20}]},"as_p2":{"total":51,"preferred_p1":[{"id":"600016579_26-41-M/01","count":11,"pct":21.6,"nazev":"SPŠ elektrotechnická, Makarenkova","obor":"Elektrotechnika","obec":"Havířov","min_body":72},{"id":"600016676_18-20-M/01","count":10,"pct":19.6,"nazev":"Střední průmyslová škola, Žižkova","obor":"Informační technologie","obec":"Karviná","min_body":68},{"id":"600016471_79-41-K/41","count":5,"pct":9.8,"nazev":"Gymnázium, J. A. Komenského","obor":"Gymnázium","obec":"Havířov","min_body":88},{"id":"600016587_18-20-M/01","count":4,"pct":7.8,"nazev":"SOŠ NET OFFICE Orlová, Energetiků","obor":"Informační technologie","obec":"Orlová","min_body":54},{"id":"600016552_36-47-M/01","count":3,"pct":5.9,"nazev":"SPŠ stavební, Kollárova","obor":"Stavebnictví","obec":"Havířov","min_body":60}],"backup_p3":[{"id":"600016536_18-20-M/01","count":6,"pct":11.8,"nazev":"Gymnázium a Obchodní akademie, Masarykova třída","obor":"Informační technologie","obec":"Orlová","min_body":40},{"id":"600016552_36-47-M/01","count":6,"pct":11.8,"nazev":"SPŠ stavební, Kollárova","obor":"Stavebnictví","obec":"Havířov","min_body":60},{"id":"600016676_18-20-M/01","count":4,"pct":7.8,"nazev":"Střední průmyslová škola, Žižkova","obor":"Informační technologie","obec":"Karviná","min_body":68},{"id":"600016587_18-20-M/01","count":3,"pct":5.9,"nazev":"SOŠ NET OFFICE Orlová, Energetiků","obor":"Informační technologie","obec":"Orlová","min_body":54}]},"as_p3":{"total":49,"preferred_p1":[{"id":"600016676_18-20-M/01","count":6,"pct":12.2,"nazev":"Střední průmyslová škola, Žižkova","obor":"Informační technologie","obec":"Karviná","min_body":68},{"id":"600016579_26-41-M/01","count":4,"pct":8.2,"nazev":"SPŠ elektrotechnická, Makarenkova","obor":"Elektrotechnika","obec":"Havířov","min_body":72},{"id":"600016552_36-47-M/01","count":4,"pct":8.2,"nazev":"SPŠ stavební, Kollárova","obor":"Stavebnictví","obec":"Havířov","min_body":60},{"id":"600016587_18-20-M/01","count":3,"pct":6.1,"nazev":"SOŠ NET OFFICE Orlová, Energetiků","obor":"Informační technologie","obec":"Orlová","min_body":54},{"id":"600016374_18-20-M/01","count":3,"pct":6.1,"nazev":"Střední škola inform.technologií, Pionýrů","obor":"Informační technologie","obec":"Frýdek-Místek","min_body":46},{"id":"600016536_18-20-M/01","count":3,"pct":6.1,"nazev":"Gymnázium a Obchodní akademie, Masarykova třída","obor":"Informační technologie","obec":"Orlová","min_body":40},{"id":"600016471_79-41-K/41","count":3,"pct":6.1,"nazev":"Gymnázium, J. A. Komenského","obor":"Gymnázium","obec":"Havířov","min_body":88},{"id":"600016269_79-41-K/41","count":3,"pct":6.1,"nazev":"Gymnázium, Komenského","obor":"Gymnázium","obec":"Třinec","min_body":122}],"preferred_p2":[{"id":"600017583_18-20-M/01","count":5,"pct":10.2,"nazev":"SPŠ elektrotechniky a informatiky, Kratochvílova","obor":"Informační technologie","obec":"Ostrava","min_body":56},{"id":"600016676_18-20-M/01","count":4,"pct":8.2,"nazev":"Střední průmyslová škola, Žižkova","obor":"Informační technologie","obec":"Karviná","min_body":68},{"id":"600016684_79-41-K/41","count":4,"pct":8.2,"nazev":"Gymnázium, Studentská","obor":"Gymnázium","obec":"Havířov","min_body":96},{"id":"600016609_63-41-M/02","count":4,"pct":8.2,"nazev":"Obchodní akademie, Sokola-Tůmy","obor":"Obchodní akademie","obec":"Český Těšín","min_body":62},{"id":"600171183_18-20-M/01","count":3,"pct":6.1,"nazev":"Střední škola, Školní","obor":"Informační technologie","obec":"Jablunkov","min_body":36},{"id":"600016471_79-41-K/41","count":3,"pct":6.1,"nazev":"Gymnázium, J. A. Komenského","obor":"Gymnázium","obec":"Havířov","min_body":88},{"id":"600016552_36-47-M/01","count":3,"pct":6.1,"nazev":"SPŠ stavební, Kollárova","obor":"Stavebnictví","obec":"Havířov","min_body":60},{"id":"600016510_26-41-M/01","count":3,"pct":6.1,"nazev":"Střední škola polytechnická, Sýkorova","obor":"Elektrotechnika","obec":"Havířov","min_body":36}]}}