{"id":"600016943_79-43-K/61","as_p1":{"total":17,"backup_p2":[{"id":"600016927_79-43-K/61","count":9,"pct":52.9,"nazev":"Gymnázium, Tomkova","obor":"Dvojjazyčné gymnázium","obec":"Olomouc","min_body":104},{"id":"600016935_79-43-K/61","count":7,"pct":41.2,"nazev":"Gymnázium, Čajkovského","obor":"Dvojjazyčné gymnázium","obec":"Olomouc","min_body":94}],"backup_p3":[{"id":"600016935_79-43-K/61","count":6,"pct":35.3,"nazev":"Gymnázium, Čajkovského","obor":"Dvojjazyčné gymnázium","obec":"Olomouc","min_body":94},{"id":"600016927_79-43-K/61","count":5,"pct":29.4,"nazev":"Gymnázium, Tomkova","obor":"Dvojjazyčné gymnázium","obec":"Olomouc","min_body":104}]},"as_p2":{"total":53,"preferred_p1":[{"id":"600016927_79-43-K/61","count":47,"pct":88.7,"nazev":"Gymnázium, Tomkova","obor":"Dvojjazyčné gymnázium","obec":"Olomouc","min_body":104},{"id":"600016935_79-43-K/61","count":4,"pct":7.5,"nazev":"Gymnázium, Čajkovského","obor":"Dvojjazyčné gymnázium","obec":"Olomouc","min_body":94}],"backup_p3":[{"id":"600016935_79-43-K/61","count":37,"pct":69.8,"nazev":"Gymnázium, Čajkovského","obor":"Dvojjazyčné gymnázium","obec":"Olomouc","min_body":94},{"id":"600016927_79-43-K/61","count":4,"pct":7.5,"nazev":"Gymnázium, Tomkova","obor":"Dvojjazyčné gymnázium","obec":"Olomouc","min_body":104}]},"as_p3":{"total":83,"preferred_p1":[{"id":"600016927_79-43-K/61","count":62,"pct":74.7,"nazev":"Gymnázium, Tomkova","obor":"Dvojjazyčné gymnázium","obec":"Olomouc","min_body":104},{"id":"600016935_79-43-K/61","count":19,"pct":22.9,"nazev":"Gymnázium, Čajkovského","obor":"Dvojjazyčné gymnázium","obec":"Olomouc","min_body":94}],"preferred_p2":[{"id":"600016935_79-43-K/61","count":60,"pct":72.3,"nazev":"Gymnázium, Čajkovského","obor":"Dvojjazyčné gymnázium","obec":"Olomouc","min_body":94},{"id":"600016927_79-43-K/61","count":20,"pct":24.1,"nazev":"Gymnázium, Tomkova","obor":"Dvojjazyčné gymnázium","obec":"Olomouc","min_body":104}]}}