{"id":"600006913_79-41-K/81","as_p1":{"total":69,"backup_p2":[{"id":"600171728_79-41-K/81","count":15,"pct":21.7,"nazev":"Sportovní gymnázium, Plzeňská","obor":"Gymnázium","obec":"Kladno","min_body":86},{"id":"600007332_79-41-K/81","count":9,"pct":13.0,"nazev":"Dvořákovo gymnázium, Dvořákovo nám.","obor":"Gymnázium","obec":"Kralupy nad Vltavou","min_body":126},{"id":"600006972_79-41-K/81","count":6,"pct":8.7,"nazev":"Gymnázium, nám. Edvarda Beneše","obor":"Gymnázium","obec":"Kladno","min_body":108},{"id":"600007952_79-41-K/81","count":4,"pct":5.8,"nazev":"Gymnázium Zikmunda Wintra, Žižkovo nám.","obor":"Gymnázium","obec":"Rakovník","min_body":96},{"id":"600010848_79-41-K/81","count":3,"pct":4.3,"nazev":"Gymnázium, Havlíčkova","obor":"Gymnázium","obec":"Roudnice nad Labem","min_body":114}],"backup_p3":[{"id":"600006972_79-41-K/81","count":13,"pct":18.8,"nazev":"Gymnázium, nám. Edvarda Beneše","obor":"Gymnázium","obec":"Kladno","min_body":108},{"id":"600171728_79-41-K/81","count":5,"pct":7.2,"nazev":"Sportovní gymnázium, Plzeňská","obor":"Gymnázium","obec":"Kladno","min_body":86},{"id":"600007332_79-41-K/81","count":3,"pct":4.3,"nazev":"Dvořákovo gymnázium, Dvořákovo nám.","obor":"Gymnázium","obec":"Kralupy nad Vltavou","min_body":126}]},"as_p2":{"total":24,"preferred_p1":[{"id":"600007332_79-41-K/81","count":7,"pct":29.2,"nazev":"Dvořákovo gymnázium, Dvořákovo nám.","obor":"Gymnázium","obec":"Kralupy nad Vltavou","min_body":126},{"id":"600007952_79-41-K/81","count":5,"pct":20.8,"nazev":"Gymnázium Zikmunda Wintra, Žižkovo nám.","obor":"Gymnázium","obec":"Rakovník","min_body":96},{"id":"600006972_79-41-K/81","count":5,"pct":20.8,"nazev":"Gymnázium, nám. Edvarda Beneše","obor":"Gymnázium","obec":"Kladno","min_body":108},{"id":"600171728_79-41-K/81","count":4,"pct":16.7,"nazev":"Sportovní gymnázium, Plzeňská","obor":"Gymnázium","obec":"Kladno","min_body":86}],"backup_p3":[]},"as_p3":{"total":31,"preferred_p1":[{"id":"600007332_79-41-K/81","count":7,"pct":22.6,"nazev":"Dvořákovo gymnázium, Dvořákovo nám.","obor":"Gymnázium","obec":"Kralupy nad Vltavou","min_body":126},{"id":"600006972_79-41-K/81","count":7,"pct":22.6,"nazev":"Gymnázium, nám. Edvarda Beneše","obor":"Gymnázium","obec":"Kladno","min_body":108},{"id":"600171728_79-41-K/81","count":5,"pct":16.1,"nazev":"Sportovní gymnázium, Plzeňská","obor":"Gymnázium","obec":"Kladno","min_body":86},{"id":"600005771_79-41-K/81","count":3,"pct":9.7,"nazev":"Gymnázium, Nad alejí","obor":"Gymnázium","obec":"Praha","min_body":154}],"preferred_p2":[{"id":"600171728_79-41-K/81","count":10,"pct":32.3,"nazev":"Sportovní gymnázium, Plzeňská","obor":"Gymnázium","obec":"Kladno","min_body":86},{"id":"600006972_79-41-K/81","count":6,"pct":19.4,"nazev":"Gymnázium, nám. Edvarda Beneše","obor":"Gymnázium","obec":"Kladno","min_body":108},{"id":"600007332_79-41-K/81","count":5,"pct":16.1,"nazev":"Dvořákovo gymnázium, Dvořákovo nám.","obor":"Gymnázium","obec":"Kralupy nad Vltavou","min_body":126}]}}