{"id":"600011763_23-45-M/01","as_p1":{"total":15,"backup_p2":[{"id":"600011763_23-68-H/01","count":4,"pct":26.7,"nazev":"600011763","obor":"","obec":"","min_body":0},{"id":"600011682_63-41-M/01","count":3,"pct":20.0,"nazev":"Gymnázium, Komenského","obor":"Ekonomika a podnikání","obec":"Nový Bydžov","min_body":48}],"backup_p3":[]},"as_p2":{"total":13,"preferred_p1":[{"id":"600012069_18-20-M/01","count":3,"pct":23.1,"nazev":"Vyšší odborná škola a SPŠ, Pod Koželuhy","obor":"Informační technologie","obec":"Jičín","min_body":66}],"backup_p3":[]},"as_p3":{"total":16,"preferred_p1":[{"id":"600011682_63-41-M/01","count":5,"pct":31.2,"nazev":"Gymnázium, Komenského","obor":"Ekonomika a podnikání","obec":"Nový Bydžov","min_body":48}],"preferred_p2":[]}}