{"id":"600018181_65-42-M/02","as_p1":{"total":25,"backup_p2":[],"backup_p3":[]},"as_p2":{"total":28,"preferred_p1":[],"backup_p3":[]},"as_p3":{"total":40,"preferred_p1":[{"id":"600018199_63-41-M/01","count":5,"pct":12.5,"nazev":"Střední škola Kostka s.r.o, Pod Pecníkem","obor":"Ekonomika a podnikání","obec":"Vsetín","min_body":38},{"id":"600018199_78-42-M/03","count":3,"pct":7.5,"nazev":"Střední škola Kostka s.r.o, Pod Pecníkem","obor":"Pedagogické lyceum","obec":"Vsetín","min_body":36}],"preferred_p2":[{"id":"600018199_78-42-M/03","count":5,"pct":12.5,"nazev":"Střední škola Kostka s.r.o, Pod Pecníkem","obor":"Pedagogické lyceum","obec":"Vsetín","min_body":36},{"id":"600018270_68-43-M/01","count":5,"pct":12.5,"nazev":"Obchodní akademie a VOŠ, Masarykova","obor":"Veřejnosprávní činnost","obec":"Valašské Meziříčí","min_body":50},{"id":"600018199_63-41-M/01","count":3,"pct":7.5,"nazev":"Střední škola Kostka s.r.o, Pod Pecníkem","obor":"Ekonomika a podnikání","obec":"Vsetín","min_body":38}]}}