{"id":"600005267_79-41-K/41","as_p1":{"total":14,"backup_p2":[],"backup_p3":[]},"as_p2":{"total":16,"preferred_p1":[],"backup_p3":[]},"as_p3":{"total":40,"preferred_p1":[{"id":"691000468_79-41-K/41","count":5,"pct":12.5,"nazev":"Gymnázium Milady Horákové, Na planině","obor":"Gymnázium","obec":"Praha","min_body":138},{"id":"600004724_79-41-K/41","count":4,"pct":10.0,"nazev":"Gymnázium, Botičská","obor":"Gymnázium","obec":"Praha","min_body":150}],"preferred_p2":[{"id":"600005054_79-41-K/41","count":3,"pct":7.5,"nazev":"Gymnázium Elišky Krásnohorské, Ohradní","obor":"Gymnázium","obec":"Praha","min_body":108},{"id":"691000468_79-41-K/41","count":3,"pct":7.5,"nazev":"Gymnázium Milady Horákové, Na planině","obor":"Gymnázium","obec":"Praha","min_body":138}]}}