{"id":"600016455_79-41-K/81","as_p1":{"total":33,"backup_p2":[{"id":"600016536_79-41-K/81","count":10,"pct":30.3,"nazev":"Gymnázium a Obchodní akademie, Masarykova třída","obor":"Gymnázium","obec":"Orlová","min_body":36},{"id":"600017508_79-41-K/81","count":4,"pct":12.1,"nazev":"Matiční gymnázium, Dr. Šmerala","obor":"Gymnázium","obec":"Ostrava","min_body":100}],"backup_p3":[]},"as_p2":{"total":22,"preferred_p1":[{"id":"600016536_79-41-K/81","count":18,"pct":81.8,"nazev":"Gymnázium a Obchodní akademie, Masarykova třída","obor":"Gymnázium","obec":"Orlová","min_body":36},{"id":"600017508_79-41-K/81","count":3,"pct":13.6,"nazev":"Matiční gymnázium, Dr. Šmerala","obor":"Gymnázium","obec":"Ostrava","min_body":100}],"backup_p3":[]},"as_p3":{"total":4,"preferred_p1":[],"preferred_p2":[]}}