{"id":"600017818_26-41-M/01","as_p1":{"total":47,"backup_p2":[{"id":"600171337_26-41-M/01","count":6,"pct":12.8,"nazev":"Střední škola elektrotechnická, Tyršova","obor":"Elektrotechnika","obec":"Lipník nad Bečvou","min_body":54},{"id":"600017818_23-41-M/01","count":5,"pct":10.6,"nazev":"Střední průmyslová škola, Havlíčkova","obor":"Strojírenství","obec":"Přerov","min_body":56},{"id":"600017818_78-42-M/01","count":3,"pct":6.4,"nazev":"Střední průmyslová škola, Havlíčkova","obor":"Technické lyceum","obec":"Přerov","min_body":70},{"id":"600171337_26-41-L/01","count":3,"pct":6.4,"nazev":"Střední škola elektrotechnická, Tyršova","obor":"Mechanik elektrotechnik","obec":"Lipník nad Bečvou","min_body":46}],"backup_p3":[{"id":"600017796_63-41-M/02","count":5,"pct":10.6,"nazev":"Obch.akademie a Jazyk.škola s právem SJZ, Bartošova","obor":"Obchodní akademie","obec":"Přerov","min_body":86},{"id":"600017818_23-41-M/01","count":4,"pct":8.5,"nazev":"Střední průmyslová škola, Havlíčkova","obor":"Strojírenství","obec":"Přerov","min_body":56},{"id":"600171337_26-41-M/01","count":3,"pct":6.4,"nazev":"Střední škola elektrotechnická, Tyršova","obor":"Elektrotechnika","obec":"Lipník nad Bečvou","min_body":54},{"id":"600171337_26-51-H/01","count":3,"pct":6.4,"nazev":"600171337","obor":"","obec":"","min_body":0}]},"as_p2":{"total":53,"preferred_p1":[{"id":"600017818_78-42-M/01","count":5,"pct":9.4,"nazev":"Střední průmyslová škola, Havlíčkova","obor":"Technické lyceum","obec":"Přerov","min_body":70},{"id":"600017818_23-41-M/01","count":5,"pct":9.4,"nazev":"Střední průmyslová škola, Havlíčkova","obor":"Strojírenství","obec":"Přerov","min_body":56}],"backup_p3":[{"id":"600017796_63-41-M/02","count":6,"pct":11.3,"nazev":"Obch.akademie a Jazyk.škola s právem SJZ, Bartošova","obor":"Obchodní akademie","obec":"Přerov","min_body":86},{"id":"600171337_26-41-M/01","count":4,"pct":7.5,"nazev":"Střední škola elektrotechnická, Tyršova","obor":"Elektrotechnika","obec":"Lipník nad Bečvou","min_body":54},{"id":"600017818_23-41-M/01","count":3,"pct":5.7,"nazev":"Střední průmyslová škola, Havlíčkova","obor":"Strojírenství","obec":"Přerov","min_body":56}]},"as_p3":{"total":26,"preferred_p1":[{"id":"600017818_78-42-M/01","count":3,"pct":11.5,"nazev":"Střední průmyslová škola, Havlíčkova","obor":"Technické lyceum","obec":"Přerov","min_body":70},{"id":"600017915_79-41-K/41","count":3,"pct":11.5,"nazev":"Gymnázium Jakuba Škody, Komenského","obor":"Gymnázium","obec":"Přerov","min_body":66},{"id":"600017176_26-41-M/01","count":3,"pct":11.5,"nazev":"VOŠ a SPŠ elektrotechnická, Božetěchova","obor":"Elektrotechnika","obec":"Olomouc","min_body":78}],"preferred_p2":[]}}