{"id":"600007251_63-41-M/02","as_p1":{"total":40,"backup_p2":[{"id":"600007251_78-42-M/02","count":19,"pct":47.5,"nazev":"VOŠ, Přemysla Otakara II.","obor":"Ekonomické lyceum","obec":"Čáslav","min_body":72},{"id":"600007278_63-41-M/01","count":6,"pct":15.0,"nazev":"Střední zemědělská škola, Sadová","obor":"Ekonomika a podnikání","obec":"Čáslav","min_body":48}],"backup_p3":[{"id":"600007278_63-41-M/01","count":10,"pct":25.0,"nazev":"Střední zemědělská škola, Sadová","obor":"Ekonomika a podnikání","obec":"Čáslav","min_body":48},{"id":"600007090_63-41-M/02","count":4,"pct":10.0,"nazev":"Obchodní akademie, Kutnohorská","obor":"Obchodní akademie","obec":"Kolín","min_body":80}]},"as_p2":{"total":44,"preferred_p1":[{"id":"600007090_63-41-M/02","count":5,"pct":11.4,"nazev":"Obchodní akademie, Kutnohorská","obor":"Obchodní akademie","obec":"Kolín","min_body":80},{"id":"600007251_78-42-M/02","count":5,"pct":11.4,"nazev":"VOŠ, Přemysla Otakara II.","obor":"Ekonomické lyceum","obec":"Čáslav","min_body":72},{"id":"600007251_23-41-M/01","count":4,"pct":9.1,"nazev":"VOŠ, Přemysla Otakara II.","obor":"Strojírenství","obec":"Čáslav","min_body":52},{"id":"600007294_68-43-M/01","count":3,"pct":6.8,"nazev":"SOŠ a SOU řemesel, Čáslavská","obor":"Veřejnosprávní činnost","obec":"Kutná Hora","min_body":52},{"id":"600007669_63-41-M/02","count":3,"pct":6.8,"nazev":"Obchodní akademie, Komenského","obor":"Obchodní akademie","obec":"Lysá nad Labem","min_body":86},{"id":"600007243_79-41-K/41","count":3,"pct":6.8,"nazev":"Gymnázium a SOŠ pedagogická, Masarykova","obor":"Gymnázium","obec":"Čáslav","min_body":84},{"id":"600007278_63-41-M/01","count":3,"pct":6.8,"nazev":"Střední zemědělská škola, Sadová","obor":"Ekonomika a podnikání","obec":"Čáslav","min_body":48}],"backup_p3":[{"id":"600007278_63-41-M/01","count":8,"pct":18.2,"nazev":"Střední zemědělská škola, Sadová","obor":"Ekonomika a podnikání","obec":"Čáslav","min_body":48},{"id":"600007251_78-42-M/02","count":4,"pct":9.1,"nazev":"VOŠ, Přemysla Otakara II.","obor":"Ekonomické lyceum","obec":"Čáslav","min_body":72},{"id":"600007090_63-41-M/02","count":3,"pct":6.8,"nazev":"Obchodní akademie, Kutnohorská","obor":"Obchodní akademie","obec":"Kolín","min_body":80},{"id":"600007294_69-41-L/01","count":3,"pct":6.8,"nazev":"SOŠ a SOU řemesel, Čáslavská","obor":"Kosmetické služby","obec":"Kutná Hora","min_body":46}]},"as_p3":{"total":56,"preferred_p1":[{"id":"600007189_63-41-M/01","count":8,"pct":14.3,"nazev":"SOŠ informatiky a spojů a SOU, Jaselská","obor":"Ekonomika a podnikání","obec":"Kolín","min_body":76},{"id":"600007243_78-42-M/03","count":6,"pct":10.7,"nazev":"Gymnázium a SOŠ pedagogická, Masarykova","obor":"Pedagogické lyceum","obec":"Čáslav","min_body":108},{"id":"600007251_78-42-M/02","count":4,"pct":7.1,"nazev":"VOŠ, Přemysla Otakara II.","obor":"Ekonomické lyceum","obec":"Čáslav","min_body":72},{"id":"600007189_18-20-M/01","count":3,"pct":5.4,"nazev":"SOŠ informatiky a spojů a SOU, Jaselská","obor":"Informační technologie","obec":"Kolín","min_body":70},{"id":"600007219_79-41-K/41","count":3,"pct":5.4,"nazev":"Gymnázium Jiřího Ortena, Jaselská","obor":"Gymnázium","obec":"Kutná Hora","min_body":140}],"preferred_p2":[{"id":"600007278_63-41-M/01","count":5,"pct":8.9,"nazev":"Střední zemědělská škola, Sadová","obor":"Ekonomika a podnikání","obec":"Čáslav","min_body":48},{"id":"600007189_63-41-M/01","count":5,"pct":8.9,"nazev":"SOŠ informatiky a spojů a SOU, Jaselská","obor":"Ekonomika a podnikání","obec":"Kolín","min_body":76},{"id":"600007294_68-43-M/01","count":4,"pct":7.1,"nazev":"SOŠ a SOU řemesel, Čáslavská","obor":"Veřejnosprávní činnost","obec":"Kutná Hora","min_body":52},{"id":"600007090_63-41-M/01","count":4,"pct":7.1,"nazev":"Obchodní akademie, Kutnohorská","obor":"Ekonomika a podnikání","obec":"Kolín","min_body":98},{"id":"600011551_36-47-M/01","count":3,"pct":5.4,"nazev":"SPŠ stavební akademika St. Bechyně, Jihlavská","obor":"Stavebnictví","obec":"Havlíčkův Brod","min_body":68},{"id":"600019527_78-42-M/04","count":3,"pct":5.4,"nazev":"Střední zdrav. škola a VOŠ zdravotnická, Karoliny Světlé","obor":"Zdravotnické lyceum","obec":"Kolín","min_body":98},{"id":"600007286_18-20-M/01","count":3,"pct":5.4,"nazev":"VOŠ, Masarykova","obor":"Informační technologie","obec":"Kutná Hora","min_body":74},{"id":"600007243_78-42-M/03","count":3,"pct":5.4,"nazev":"Gymnázium a SOŠ pedagogická, Masarykova","obor":"Pedagogické lyceum","obec":"Čáslav","min_body":108},{"id":"600007090_78-42-M/02","count":3,"pct":5.4,"nazev":"Obchodní akademie, Kutnohorská","obor":"Ekonomické lyceum","obec":"Kolín","min_body":96},{"id":"600170136_36-47-M/01","count":3,"pct":5.4,"nazev":"SOŠ stavební a SOU stavební, Pražská","obor":"Stavebnictví","obec":"Kolín","min_body":60}]}}