{"id":"600005348_79-41-K/81","as_p1":{"total":238,"backup_p2":[{"id":"600005208_79-41-K/81","count":65,"pct":27.3,"nazev":"Gymnázium Opatov, Konstantinova","obor":"Gymnázium","obec":"Praha","min_body":130},{"id":"600005054_79-41-K/81","count":57,"pct":23.9,"nazev":"Gymnázium Elišky Krásnohorské, Ohradní","obor":"Gymnázium","obec":"Praha","min_body":128},{"id":"600005046_79-41-K/81","count":34,"pct":14.3,"nazev":"Gymnázium, Písnická","obor":"Gymnázium","obec":"Praha","min_body":124},{"id":"600006603_79-41-K/81","count":11,"pct":4.6,"nazev":"Gymnázium, Voděradská","obor":"Gymnázium","obec":"Praha","min_body":142},{"id":"600004694_79-41-K/81","count":7,"pct":2.9,"nazev":"Gymnázium prof. Jana Patočky, Jindřišská","obor":"Gymnázium","obec":"Praha","min_body":152},{"id":"600006646_79-41-K/81","count":7,"pct":2.9,"nazev":"Gymnázium, Omská","obor":"Gymnázium","obec":"Praha","min_body":130},{"id":"600005267_79-41-K/81","count":6,"pct":2.5,"nazev":"Klasické gymnázium Modřany a ZŠ, Rakovského","obor":"Gymnázium","obec":"Praha","min_body":82},{"id":"600005518_79-41-K/81","count":6,"pct":2.5,"nazev":"Gymnázium Christiana Dopplera, Zborovská","obor":"Gymnázium","obec":"Praha","min_body":150},{"id":"600005623_79-41-K/81","count":4,"pct":1.7,"nazev":"Gymnázium, Nad Kavalírkou","obor":"Gymnázium","obec":"Praha","min_body":120},{"id":"600005534_79-41-K/81","count":3,"pct":1.3,"nazev":"Gymnázium Jaroslava Heyrovského, Mezi školami","obor":"Gymnázium","obec":"Praha","min_body":124}],"backup_p3":[{"id":"600005054_79-41-K/81","count":44,"pct":18.5,"nazev":"Gymnázium Elišky Krásnohorské, Ohradní","obor":"Gymnázium","obec":"Praha","min_body":128},{"id":"600005046_79-41-K/81","count":32,"pct":13.4,"nazev":"Gymnázium, Písnická","obor":"Gymnázium","obec":"Praha","min_body":124},{"id":"600005208_79-41-K/81","count":32,"pct":13.4,"nazev":"Gymnázium Opatov, Konstantinova","obor":"Gymnázium","obec":"Praha","min_body":130},{"id":"600005267_79-41-K/81","count":17,"pct":7.1,"nazev":"Klasické gymnázium Modřany a ZŠ, Rakovského","obor":"Gymnázium","obec":"Praha","min_body":82},{"id":"600006603_79-41-K/81","count":11,"pct":4.6,"nazev":"Gymnázium, Voděradská","obor":"Gymnázium","obec":"Praha","min_body":142},{"id":"600006646_79-41-K/81","count":10,"pct":4.2,"nazev":"Gymnázium, Omská","obor":"Gymnázium","obec":"Praha","min_body":130},{"id":"600006476_79-41-K/81","count":7,"pct":2.9,"nazev":"Křesťanské gymnázium, Kozinova","obor":"Gymnázium","obec":"Praha","min_body":100},{"id":"600005623_79-41-K/81","count":4,"pct":1.7,"nazev":"Gymnázium, Nad Kavalírkou","obor":"Gymnázium","obec":"Praha","min_body":120},{"id":"600005518_79-41-K/81","count":4,"pct":1.7,"nazev":"Gymnázium Christiana Dopplera, Zborovská","obor":"Gymnázium","obec":"Praha","min_body":150},{"id":"600004791_79-41-K/81","count":3,"pct":1.3,"nazev":"Arcibiskupské gymnázium, Korunní","obor":"Gymnázium","obec":"Praha","min_body":120}]},"as_p2":{"total":216,"preferred_p1":[{"id":"600005208_79-41-K/81","count":50,"pct":23.1,"nazev":"Gymnázium Opatov, Konstantinova","obor":"Gymnázium","obec":"Praha","min_body":130},{"id":"600005054_79-41-K/81","count":34,"pct":15.7,"nazev":"Gymnázium Elišky Krásnohorské, Ohradní","obor":"Gymnázium","obec":"Praha","min_body":128},{"id":"600005046_79-41-K/81","count":31,"pct":14.4,"nazev":"Gymnázium, Písnická","obor":"Gymnázium","obec":"Praha","min_body":124},{"id":"600006018_79-41-K/81","count":18,"pct":8.3,"nazev":"PORG - gymnázium, Rostislavova","obor":"Gymnázium","obec":"Ostrava","min_body":90},{"id":"600006603_79-41-K/81","count":10,"pct":4.6,"nazev":"Gymnázium, Voděradská","obor":"Gymnázium","obec":"Praha","min_body":142},{"id":"600005518_79-41-K/81","count":9,"pct":4.2,"nazev":"Gymnázium Christiana Dopplera, Zborovská","obor":"Gymnázium","obec":"Praha","min_body":150},{"id":"600005623_79-41-K/81","count":6,"pct":2.8,"nazev":"Gymnázium, Nad Kavalírkou","obor":"Gymnázium","obec":"Praha","min_body":120},{"id":"600005771_79-41-K/81","count":6,"pct":2.8,"nazev":"Gymnázium, Nad alejí","obor":"Gymnázium","obec":"Praha","min_body":154},{"id":"600004791_79-41-K/81","count":6,"pct":2.8,"nazev":"Arcibiskupské gymnázium, Korunní","obor":"Gymnázium","obec":"Praha","min_body":120},{"id":"600007766_79-41-K/81","count":5,"pct":2.3,"nazev":"Gymnázium, Komenského náměstí","obor":"Gymnázium","obec":"Říčany","min_body":146}],"backup_p3":[{"id":"600005054_79-41-K/81","count":41,"pct":19.0,"nazev":"Gymnázium Elišky Krásnohorské, Ohradní","obor":"Gymnázium","obec":"Praha","min_body":128},{"id":"600005208_79-41-K/81","count":28,"pct":13.0,"nazev":"Gymnázium Opatov, Konstantinova","obor":"Gymnázium","obec":"Praha","min_body":130},{"id":"600005046_79-41-K/81","count":22,"pct":10.2,"nazev":"Gymnázium, Písnická","obor":"Gymnázium","obec":"Praha","min_body":124},{"id":"600006476_79-41-K/81","count":13,"pct":6.0,"nazev":"Křesťanské gymnázium, Kozinova","obor":"Gymnázium","obec":"Praha","min_body":100},{"id":"600006646_79-41-K/81","count":12,"pct":5.6,"nazev":"Gymnázium, Omská","obor":"Gymnázium","obec":"Praha","min_body":130},{"id":"600005534_79-41-K/81","count":8,"pct":3.7,"nazev":"Gymnázium Jaroslava Heyrovského, Mezi školami","obor":"Gymnázium","obec":"Praha","min_body":124},{"id":"600006603_79-41-K/81","count":8,"pct":3.7,"nazev":"Gymnázium, Voděradská","obor":"Gymnázium","obec":"Praha","min_body":142},{"id":"600005267_79-41-K/81","count":7,"pct":3.2,"nazev":"Klasické gymnázium Modřany a ZŠ, Rakovského","obor":"Gymnázium","obec":"Praha","min_body":82},{"id":"600004694_79-41-K/81","count":6,"pct":2.8,"nazev":"Gymnázium prof. Jana Patočky, Jindřišská","obor":"Gymnázium","obec":"Praha","min_body":152},{"id":"600007766_79-41-K/81","count":5,"pct":2.3,"nazev":"Gymnázium, Komenského náměstí","obor":"Gymnázium","obec":"Říčany","min_body":146}]},"as_p3":{"total":151,"preferred_p1":[{"id":"600005208_79-41-K/81","count":29,"pct":19.2,"nazev":"Gymnázium Opatov, Konstantinova","obor":"Gymnázium","obec":"Praha","min_body":130},{"id":"600005046_79-41-K/81","count":19,"pct":12.6,"nazev":"Gymnázium, Písnická","obor":"Gymnázium","obec":"Praha","min_body":124},{"id":"600005054_79-41-K/81","count":15,"pct":9.9,"nazev":"Gymnázium Elišky Krásnohorské, Ohradní","obor":"Gymnázium","obec":"Praha","min_body":128},{"id":"600006603_79-41-K/81","count":11,"pct":7.3,"nazev":"Gymnázium, Voděradská","obor":"Gymnázium","obec":"Praha","min_body":142},{"id":"600006018_79-41-K/81","count":10,"pct":6.6,"nazev":"PORG - gymnázium, Rostislavova","obor":"Gymnázium","obec":"Ostrava","min_body":90},{"id":"600005518_79-41-K/81","count":9,"pct":6.0,"nazev":"Gymnázium Christiana Dopplera, Zborovská","obor":"Gymnázium","obec":"Praha","min_body":150},{"id":"600006646_79-41-K/81","count":6,"pct":4.0,"nazev":"Gymnázium, Omská","obor":"Gymnázium","obec":"Praha","min_body":130},{"id":"600004791_79-41-K/81","count":6,"pct":4.0,"nazev":"Arcibiskupské gymnázium, Korunní","obor":"Gymnázium","obec":"Praha","min_body":120},{"id":"600006476_79-41-K/81","count":6,"pct":4.0,"nazev":"Křesťanské gymnázium, Kozinova","obor":"Gymnázium","obec":"Praha","min_body":100},{"id":"600005691_79-41-K/81","count":5,"pct":3.3,"nazev":"Gymnázium Jana Keplera, Parléřova","obor":"Gymnázium","obec":"Praha","min_body":162}],"preferred_p2":[{"id":"600005054_79-41-K/81","count":24,"pct":15.9,"nazev":"Gymnázium Elišky Krásnohorské, Ohradní","obor":"Gymnázium","obec":"Praha","min_body":128},{"id":"600005046_79-41-K/81","count":20,"pct":13.2,"nazev":"Gymnázium, Písnická","obor":"Gymnázium","obec":"Praha","min_body":124},{"id":"600005208_79-41-K/81","count":17,"pct":11.3,"nazev":"Gymnázium Opatov, Konstantinova","obor":"Gymnázium","obec":"Praha","min_body":130},{"id":"600006476_79-41-K/81","count":14,"pct":9.3,"nazev":"Křesťanské gymnázium, Kozinova","obor":"Gymnázium","obec":"Praha","min_body":100},{"id":"600006603_79-41-K/81","count":11,"pct":7.3,"nazev":"Gymnázium, Voděradská","obor":"Gymnázium","obec":"Praha","min_body":142},{"id":"600005518_79-41-K/81","count":8,"pct":5.3,"nazev":"Gymnázium Christiana Dopplera, Zborovská","obor":"Gymnázium","obec":"Praha","min_body":150},{"id":"600006646_79-41-K/81","count":7,"pct":4.6,"nazev":"Gymnázium, Omská","obor":"Gymnázium","obec":"Praha","min_body":130},{"id":"600004597_79-41-K/81","count":5,"pct":3.3,"nazev":"Malostranské gymnázium, Josefská","obor":"Gymnázium","obec":"Praha","min_body":152},{"id":"600005178_79-41-K/81","count":5,"pct":3.3,"nazev":"Gymnázium Evolution, Sázavská","obor":"Gymnázium","obec":"Praha","min_body":136},{"id":"600006018_79-41-K/81","count":4,"pct":2.6,"nazev":"PORG - gymnázium, Rostislavova","obor":"Gymnázium","obec":"Ostrava","min_body":90}]}}