{"id":"600008886_26-45-M/01","as_p1":{"total":5,"backup_p2":[],"backup_p3":[]},"as_p2":{"total":18,"preferred_p1":[{"id":"600008886_18-20-M/01","count":10,"pct":55.6,"nazev":"Střední škola spojů a informatiky, Bydlinského","obor":"Informační technologie","obec":"Tábor","min_body":78},{"id":"600008886_26-41-L/01","count":5,"pct":27.8,"nazev":"Střední škola spojů a informatiky, Bydlinského","obor":"Mechanik elektrotechnik","obec":"Tábor","min_body":78}],"backup_p3":[{"id":"600170438_18-20-M/01","count":3,"pct":16.7,"nazev":"VOŠ, Budějovická","obor":"Informační technologie","obec":"Sezimovo Ústí","min_body":70}]},"as_p3":{"total":8,"preferred_p1":[{"id":"600008886_18-20-M/01","count":5,"pct":62.5,"nazev":"Střední škola spojů a informatiky, Bydlinského","obor":"Informační technologie","obec":"Tábor","min_body":78}],"preferred_p2":[{"id":"600170438_18-20-M/01","count":3,"pct":37.5,"nazev":"VOŠ, Budějovická","obor":"Informační technologie","obec":"Sezimovo Ústí","min_body":70}]}}