{"id":"600170730_79-41-K/41","as_p1":{"total":12,"backup_p2":[{"id":"600170730_75-41-M/01","count":4,"pct":33.3,"nazev":"Akademie Světlá n. S., Sázavská","obor":"Sociální činnost","obec":"Světlá nad Sázavou","min_body":32}],"backup_p3":[]},"as_p2":{"total":26,"preferred_p1":[{"id":"600011500_79-41-K/41","count":7,"pct":26.9,"nazev":"Gymnázium Havlíčkův Brod, Štáflova","obor":"Gymnázium","obec":"Havlíčkův Brod","min_body":108},{"id":"600011534_79-41-K/41","count":3,"pct":11.5,"nazev":"Gymnázium, Husovo náměstí","obor":"Gymnázium","obec":"Ledeč nad Sázavou","min_body":24}],"backup_p3":[{"id":"600019756_78-42-M/04","count":4,"pct":15.4,"nazev":"Střední zdravot.škola a VOŠ zdravotnická, Masarykova","obor":"Zdravotnické lyceum","obec":"Havlíčkův Brod","min_body":76}]},"as_p3":{"total":31,"preferred_p1":[{"id":"600011500_79-41-K/41","count":5,"pct":16.1,"nazev":"Gymnázium Havlíčkův Brod, Štáflova","obor":"Gymnázium","obec":"Havlíčkův Brod","min_body":108},{"id":"600011534_79-41-K/41","count":4,"pct":12.9,"nazev":"Gymnázium, Husovo náměstí","obor":"Gymnázium","obec":"Ledeč nad Sázavou","min_body":24}],"preferred_p2":[{"id":"600007243_79-41-K/41","count":3,"pct":9.7,"nazev":"Gymnázium a SOŠ pedagogická, Masarykova","obor":"Gymnázium","obec":"Čáslav","min_body":84}]}}