{"id":"691012415_63-41-M/02","as_p1":{"total":37,"backup_p2":[{"id":"600012271_78-42-M/02","count":6,"pct":16.2,"nazev":"ACADEMIA MERCURII soukromá SŠ, Smiřických","obor":"Ekonomické lyceum","obec":"Náchod","min_body":76},{"id":"600019829_63-41-M/02","count":5,"pct":13.5,"nazev":"VOŠ zdrav., Procházkova","obor":"Obchodní akademie","obec":"Trutnov","min_body":76},{"id":"600012271_65-42-M/02","count":3,"pct":8.1,"nazev":"ACADEMIA MERCURII soukromá SŠ, Smiřických","obor":"Cestovní ruch","obec":"Náchod","min_body":50}],"backup_p3":[{"id":"600012271_65-42-M/02","count":3,"pct":8.1,"nazev":"ACADEMIA MERCURII soukromá SŠ, Smiřických","obor":"Cestovní ruch","obec":"Náchod","min_body":50},{"id":"691012415_18-20-M/01","count":3,"pct":8.1,"nazev":"SPŠ stav. a OA arch. J. Letzela, Pražská","obor":"Informační technologie","obec":"Náchod","min_body":54}]},"as_p2":{"total":67,"preferred_p1":[{"id":"600012115_79-41-K/41","count":11,"pct":16.4,"nazev":"Jiráskovo gymnázium, Řezníčkova","obor":"Gymnázium","obec":"Náchod","min_body":112},{"id":"600012271_78-42-M/02","count":7,"pct":10.4,"nazev":"ACADEMIA MERCURII soukromá SŠ, Smiřických","obor":"Ekonomické lyceum","obec":"Náchod","min_body":76},{"id":"691012415_36-47-M/01","count":6,"pct":9.0,"nazev":"SPŠ stav. a OA arch. J. Letzela, Pražská","obor":"Stavebnictví","obec":"Náchod","min_body":56},{"id":"600011739_63-41-M/02","count":5,"pct":7.5,"nazev":"OA, Pospíšilova","obor":"Obchodní akademie","obec":"Hradec Králové","min_body":110},{"id":"600012271_65-42-M/02","count":5,"pct":7.5,"nazev":"ACADEMIA MERCURII soukromá SŠ, Smiřických","obor":"Cestovní ruch","obec":"Náchod","min_body":50},{"id":"600019829_63-41-M/02","count":4,"pct":6.0,"nazev":"VOŠ zdrav., Procházkova","obor":"Obchodní akademie","obec":"Trutnov","min_body":76},{"id":"691012415_18-20-M/01","count":4,"pct":6.0,"nazev":"SPŠ stav. a OA arch. J. Letzela, Pražská","obor":"Informační technologie","obec":"Náchod","min_body":54},{"id":"691012440_65-42-M/01","count":3,"pct":4.5,"nazev":"SŠ hotelnictví, Pražská","obor":"Hotelnictví","obec":"Trutnov","min_body":46}],"backup_p3":[{"id":"600012271_78-42-M/02","count":7,"pct":10.4,"nazev":"ACADEMIA MERCURII soukromá SŠ, Smiřických","obor":"Ekonomické lyceum","obec":"Náchod","min_body":76},{"id":"600012271_65-42-M/02","count":5,"pct":7.5,"nazev":"ACADEMIA MERCURII soukromá SŠ, Smiřických","obor":"Cestovní ruch","obec":"Náchod","min_body":50},{"id":"600012123_79-41-K/41","count":4,"pct":6.0,"nazev":"Gymnázium Jaroslava Žáka, Lužická","obor":"Gymnázium","obec":"Jaroměř","min_body":52},{"id":"600024211_18-20-M/01","count":4,"pct":6.0,"nazev":"SPŠ, Československé armády","obor":"Informační technologie","obec":"Nové Město nad Metují","min_body":46},{"id":"691012415_36-47-M/01","count":4,"pct":6.0,"nazev":"SPŠ stav. a OA arch. J. Letzela, Pražská","obor":"Stavebnictví","obec":"Náchod","min_body":56},{"id":"600011739_63-41-M/02","count":3,"pct":4.5,"nazev":"OA, Pospíšilova","obor":"Obchodní akademie","obec":"Hradec Králové","min_body":110},{"id":"600012115_79-41-K/41","count":3,"pct":4.5,"nazev":"Jiráskovo gymnázium, Řezníčkova","obor":"Gymnázium","obec":"Náchod","min_body":112},{"id":"610200381_18-20-M/01","count":3,"pct":4.5,"nazev":"Střední průmyslová škola, Školní","obor":"Informační technologie","obec":"Trutnov","min_body":82},{"id":"691012431_26-51-H/01","count":3,"pct":4.5,"nazev":"691012431","obor":"","obec":"","min_body":0}]},"as_p3":{"total":92,"preferred_p1":[{"id":"600012115_79-41-K/41","count":16,"pct":17.4,"nazev":"Jiráskovo gymnázium, Řezníčkova","obor":"Gymnázium","obec":"Náchod","min_body":112},{"id":"600012271_78-42-M/02","count":11,"pct":12.0,"nazev":"ACADEMIA MERCURII soukromá SŠ, Smiřických","obor":"Ekonomické lyceum","obec":"Náchod","min_body":76},{"id":"600012107_79-41-K/41","count":7,"pct":7.6,"nazev":"Gymnázium, Hradební","obor":"Gymnázium","obec":"Broumov","min_body":62},{"id":"600012271_65-42-M/02","count":4,"pct":4.3,"nazev":"ACADEMIA MERCURII soukromá SŠ, Smiřických","obor":"Cestovní ruch","obec":"Náchod","min_body":50},{"id":"600012549_79-41-K/41","count":4,"pct":4.3,"nazev":"Gymnázium, Pulická","obor":"Gymnázium","obec":"Dobruška","min_body":100},{"id":"600011739_63-41-M/02","count":3,"pct":3.3,"nazev":"OA, Pospíšilova","obor":"Obchodní akademie","obec":"Hradec Králové","min_body":110},{"id":"651014271_68-42-M/01","count":3,"pct":3.3,"nazev":"Bezpečnostně právní akademie, 17. listopadu","obor":"Bezpečnostně právní činnost","obec":"Malé Svatoňovice","min_body":78},{"id":"600019829_63-41-M/02","count":3,"pct":3.3,"nazev":"VOŠ zdrav., Procházkova","obor":"Obchodní akademie","obec":"Trutnov","min_body":76}],"preferred_p2":[{"id":"600012115_79-41-K/41","count":14,"pct":15.2,"nazev":"Jiráskovo gymnázium, Řezníčkova","obor":"Gymnázium","obec":"Náchod","min_body":112},{"id":"600012271_78-42-M/02","count":7,"pct":7.6,"nazev":"ACADEMIA MERCURII soukromá SŠ, Smiřických","obor":"Ekonomické lyceum","obec":"Náchod","min_body":76},{"id":"600012271_65-42-M/02","count":5,"pct":5.4,"nazev":"ACADEMIA MERCURII soukromá SŠ, Smiřických","obor":"Cestovní ruch","obec":"Náchod","min_body":50},{"id":"600012107_79-41-K/41","count":5,"pct":5.4,"nazev":"Gymnázium, Hradební","obor":"Gymnázium","obec":"Broumov","min_body":62},{"id":"600012123_79-41-K/41","count":5,"pct":5.4,"nazev":"Gymnázium Jaroslava Žáka, Lužická","obor":"Gymnázium","obec":"Jaroměř","min_body":52},{"id":"691012415_36-47-M/01","count":5,"pct":5.4,"nazev":"SPŠ stav. a OA arch. J. Letzela, Pražská","obor":"Stavebnictví","obec":"Náchod","min_body":56},{"id":"600011739_63-41-M/02","count":4,"pct":4.3,"nazev":"OA, Pospíšilova","obor":"Obchodní akademie","obec":"Hradec Králové","min_body":110},{"id":"600012581_63-41-M/02","count":3,"pct":3.3,"nazev":"Obchodní akademie T. G. Masaryka, Komenského","obor":"Obchodní akademie","obec":"Kostelec nad Orlicí","min_body":74},{"id":"651014646_68-42-M/01","count":3,"pct":3.3,"nazev":"TRIVIS-Střední škola veřejnoprávní s.r.o, Heldovo náměstí","obor":"Bezpečnostně právní činnost","obec":"Třebechovice pod Orebem","min_body":72},{"id":"600019829_53-41-M/03","count":3,"pct":3.3,"nazev":"VOŠ zdrav., Procházkova","obor":"Praktická sestra","obec":"Trutnov","min_body":76}]}}