{"id":"691003009_79-41-K/81","as_p1":{"total":56,"backup_p2":[{"id":"600012310_79-41-K/81","count":17,"pct":30.4,"nazev":"Gymnázium, Dašická","obor":"Gymnázium","obec":"Pardubice","min_body":100}],"backup_p3":[]},"as_p2":{"total":12,"preferred_p1":[{"id":"600012310_79-41-K/81","count":11,"pct":91.7,"nazev":"Gymnázium, Dašická","obor":"Gymnázium","obec":"Pardubice","min_body":100}],"backup_p3":[]},"as_p3":{"total":8,"preferred_p1":[{"id":"600012310_79-41-K/81","count":5,"pct":62.5,"nazev":"Gymnázium, Dašická","obor":"Gymnázium","obec":"Pardubice","min_body":100}],"preferred_p2":[{"id":"600011887_79-41-K/81","count":3,"pct":37.5,"nazev":"Gymnázium Josefa Ressela, Olbrachtova","obor":"Gymnázium","obec":"Chrudim","min_body":86}]}}